README.md
setup.cfg
setup.py
dracaufeu/__init__.py
dracaufeu.egg-info/PKG-INFO
dracaufeu.egg-info/SOURCES.txt
dracaufeu.egg-info/dependency_links.txt
dracaufeu.egg-info/top_level.txt
dracaufeu/utils/__init__.py
dracaufeu/utils/data/__init__.py
dracaufeu/utils/data/datasets.py
dracaufeu/utils/image/__init__.py
dracaufeu/utils/image/transforms.py