Metadata-Version: 1.1
Name: dracaufeu
Version: 0.6
Summary: Pytorch extension package for personal use
Home-page: https://github.com/Etienne-Meunier/dracaufeu
Author: Etienne Meunier
Author-email: etiennemeunier@live.fr
License: MIT
Download-URL: https://github.com/Etienne-Meunier/dracaufeu/archive/v_06.tar.gz
Keywords: Pytorch,DeepLearning
Platform: UNKNOWN
Classifier: Development Status :: 3 - Alpha
Classifier: Intended Audience :: Developers
Classifier: Topic :: Software Development :: Build Tools
Classifier: License :: OSI Approved :: MIT License
Classifier: Programming Language :: Python :: 3
Classifier: Programming Language :: Python :: 3.4
Classifier: Programming Language :: Python :: 3.5
Classifier: Programming Language :: Python :: 3.6
